Tiefenmoser_Cornelius_Versuch1_Aufgabe1/Komponenten/RAM/Single_Port_RAM.vhdl
library ieee;
use ieee.std_logic_1164.all;
use ieee.numeric_std.all;
use work.constant_package.all;

entity single_port_ram is
    generic(
        G_word_width : integer := WORD_WIDTH;
        G_addr_width : integer := ADR_WIDTH
    );
    port(
        pi_data : in std_logic_vector (G_word_width-1 downto 0) := (others => '0');
        pi_addr : in std_logic_vector (G_addr_width-1 downto 0) := (others => '0');
        pi_we,pi_clk,pi_rst : in std_logic := '0';
        
        po_data : out std_logic_vector(G_word_width-1 downto 0) := (others => '0')
    );
end entity;


architecture behavior of single_port_ram is
    type memory_array is array (0 to G_addr_width-1) of std_logic_vector(G_word_width-1 downto 0);
    signal RAM : memory_array := (others => (others => '0'));

begin
    ram_process: process (pi_clk,pi_rst,pi_we)
        begin
            if(pi_rst = '1') then 
                RAM <= (others => (others => '0')); -- set all bits of the memory array to 0
                po_data <= RAM(to_integer(unsigned(pi_addr)));
            elsif rising_edge(pi_clk) then
                if(pi_we = '1') then --why is this delayed by an entire cycle
                    RAM(to_integer(unsigned(pi_addr))) <= pi_data;
                end if;
                po_data <= RAM(to_integer(unsigned(pi_addr)));
            end if;
        end process;
end architecture;

Tiefenmoser_Cornelius_Versuch1_Aufgabe1/Testbenches/RAM/Single_Port_RAM_tb.vhdl
library ieee;
use ieee.std_logic_1164.all;
use ieee.math_real.all;
use ieee.numeric_std.all;
use work.constant_package.all;




entity Single_Port_RAM_tb is
end entity;


architecture behavior of Single_Port_RAM_tb is
    signal s_clk, s_rst, s_we: std_logic := '0';
    
    
    signal s_addr : std_logic_vector (31 downto 0) := (others => '0');
    signal s_data : std_logic_vector(15 downto 0);
    signal s_dataout :std_logic_vector (15 downto 0);
    signal s_expected : std_logic_vector( 15 downto 0);
    
    -- Why do i get different results for different clock times??????
    constant c_clk_period : time := 10 ns;

    begin
    -- CLK Process aus der übung von Stefanie Häberle 
    clk_process : process
        begin
            while now < 400 ns loop  -- Simulation fuer 200 ns
                s_clk <= '0';
                wait for c_clk_period / 2;
                s_clk <= '1';
                wait for c_clk_period / 2;
            end loop;
            wait;
    end process;

    ram:entity work.single_port_ram
        generic map(16,32)
        port map(
            pi_data => s_data,
            pi_addr => s_addr,
            
            pi_we => s_we,
            pi_clk => s_clk,
            pi_rst => s_rst,

            po_data => s_dataout
        );


    spr_test: process is             
        begin
            s_addr <= (others => '0');
            -- the 32 is there for a reason since 2**0 != 000....00 and we want to test from 0 to 2**31
            for i in 0 to 31 loop

                s_data <= (others => '1');
                s_we <= '1'; 
                s_expected <= (others => '0');
                s_rst <= '1';
                wait for c_clk_period;
                assert(s_dataout = s_expected) report ("Doesnt reset to 0") severity error;
                
                
                s_rst <= '0'; 
                s_data <= (others => '1');
                s_we <= '1'; 
                s_expected <= (others => '1');
                wait for c_clk_period;
                assert(s_dataout = s_expected) report ("Data doesnt set to 1 with we = 1 actual value of s_dataout: " & to_string(s_dataout))
                severity error;

                s_data <= (others => '0');
                s_we <= '1'; 
                s_expected <= (others => '0');
                wait for c_clk_period;
                assert(s_dataout = s_expected) report ("Data doesnt set to 0 with we = 1 actual value of s_dataout: " & to_string(s_dataout)) 
                severity error;

                s_data <= (others => '1');
                s_we <= '0'; 
                s_expected <= (others => '0');
                wait for c_clk_period;
                assert(s_dataout = s_expected) report ("Data sets to 1 despite we = 0") severity error;

                assert false report "End of test for address: " & to_string(s_addr) severity note;
                s_addr <= std_logic_vector(to_unsigned(2 ** i,s_addr'length) );
            end loop;
        end process;                


end architecture;

Tiefenmoser_Cornelius_Versuch1_Aufgabe1/ram_tb.vcd
$date
  Sun May  4 21:33:22 2025
$end
$version
  GHDL v0
$end
$timescale
  1 fs
$end
$scope module standard $end
$upscope $end
$scope module textio $end
$upscope $end
$scope module std_logic_1164 $end
$upscope $end
$scope module math_real $end
$upscope $end
$scope module numeric_std $end
$upscope $end
$scope module constant_package $end
$upscope $end
$scope module single_port_ram_tb $end
$var reg 1 ! s_clk $end
$var reg 1 " s_rst $end
$var reg 1 # s_we $end
$var reg 32 $ s_addr[31:0] $end
$var reg 16 % s_data[15:0] $end
$var reg 16 & s_dataout[15:0] $end
$var reg 16 ' s_expected[15:0] $end
$scope module ram $end
$var reg 16 ( pi_data[15:0] $end
$var reg 32 ) pi_addr[31:0] $end
$var reg 1 * pi_we $end
$var reg 1 + pi_clk $end
$var reg 1 , pi_rst $end
$var reg 16 - po_data[15:0] $end
$comment ram is not handled $end
$upscope $end
$upscope $end
$enddefinitions $end
#0
0!
1"
1#
b00000000000000000000000000000000 $
b1111111111111111 %
b0000000000000000 &
b0000000000000000 '
b1111111111111111 (
b00000000000000000000000000000000 )
1*
0+
1,
b0000000000000000 -
#5000000
1!
1+
#10000000
0!
0"
b1111111111111111 '
0+
0,
#15000000
1!
1+
#20000000
0!
b0000000000000000 %
b0000000000000000 '
b0000000000000000 (
0+
#25000000
1!
b1111111111111111 &
1+
b1111111111111111 -
#30000000
0!
0#
b1111111111111111 %
b1111111111111111 (
0*
0+
#35000000
1!
b0000000000000000 &
1+
b0000000000000000 -
#40000000
0!
1"
1#
b00000000000000000000000000000001 $
b00000000000000000000000000000001 )
1*
0+
1,
#45000000
1!
1+
#50000000
0!
0"
b1111111111111111 '
0+
0,
#55000000
1!
1+
#60000000
0!
b0000000000000000 %
b0000000000000000 '
b0000000000000000 (
0+
#65000000
1!
b1111111111111111 &
1+
b1111111111111111 -
#70000000
0!
0#
b1111111111111111 %
b1111111111111111 (
0*
0+
#75000000
1!
b0000000000000000 &
1+
b0000000000000000 -
#80000000
0!
1"
1#
b00000000000000000000000000000010 $
b00000000000000000000000000000010 )
1*
0+
1,
#85000000
1!
1+
#90000000
0!
0"
b1111111111111111 '
0+
0,
#95000000
1!
1+
#100000000
0!
b0000000000000000 %
b0000000000000000 '
b0000000000000000 (
0+
#105000000
1!
b1111111111111111 &
1+
b1111111111111111 -
#110000000
0!
0#
b1111111111111111 %
b1111111111111111 (
0*
0+
#115000000
1!
b0000000000000000 &
1+
b0000000000000000 -
#120000000
0!
1"
1#
b00000000000000000000000000000100 $
b00000000000000000000000000000100 )
1*
0+
1,
#125000000
1!
1+
#130000000
0!
0"
b1111111111111111 '
0+
0,
#135000000
1!
1+
#140000000
0!
b0000000000000000 %
b0000000000000000 '
b0000000000000000 (
0+
#145000000
1!
b1111111111111111 &
1+
b1111111111111111 -
#150000000
0!
0#
b1111111111111111 %
b1111111111111111 (
0*
0+
#155000000
1!
b0000000000000000 &
1+
b0000000000000000 -
#160000000
0!
1"
1#
b00000000000000000000000000001000 $
b00000000000000000000000000001000 )
1*
0+
1,
#165000000
1!
1+
#170000000
0!
0"
b1111111111111111 '
0+
0,
#175000000
1!
1+
#180000000
0!
b0000000000000000 %
b0000000000000000 '
b0000000000000000 (
0+
#185000000
1!
b1111111111111111 &
1+
b1111111111111111 -
#190000000
0!
0#
b1111111111111111 %
b1111111111111111 (
0*
0+
#195000000
1!
b0000000000000000 &
1+
b0000000000000000 -
#200000000
0!
1"
1#
b00000000000000000000000000010000 $
b00000000000000000000000000010000 )
1*
0+
1,
#205000000
1!
1+
#210000000
0!
0"
b1111111111111111 '
0+
0,
#215000000
1!
1+
#220000000
0!
b0000000000000000 %
b0000000000000000 '
b0000000000000000 (
0+
#225000000
1!
b1111111111111111 &
1+
b1111111111111111 -
#230000000
0!
0#
b1111111111111111 %
b1111111111111111 (
0*
0+
#235000000
1!
b0000000000000000 &
1+
b0000000000000000 -
