Tiefenmoser_Cornelius_Versuch1_Aufgabe1/Komponenten/RAM/Single_Port_RAM.vhdl
library ieee;
use ieee.std_logic_1164.all;
use ieee.numeric_std.all;
use work.constant_package.all;

entity single_port_ram is
    generic(
        G_word_width : integer := WORD_WIDTH;
        G_addr_width : integer := ADR_WIDTH
    );
    port(
        pi_data : in std_logic_vector (G_word_width-1 downto 0) := (others => '0');
        pi_addr : in std_logic_vector (G_addr_width-1 downto 0) := (others => '0');
        pi_we,pi_rst : in std_logic := '0';
        pi_clk : in std_logic;
        po_data : out std_logic_vector(G_word_width-1 downto 0) := (others => '0')
    );
end entity;


architecture behavior of single_port_ram is
    type memory_array is array (0 to 2 ** 16 - 1) of std_logic_vector(G_word_width-1 downto 0);
    signal RAM : memory_array := (others => (others => '0'));

begin
    ram_process: process (pi_rst,pi_clk)
        begin
            if pi_rst = '1' then 
                RAM <= (others => (others => '0')); 
                po_data <= RAM(to_integer(unsigned(pi_addr))); -- TODO: this might have the update problem too might need the fix to but idk removes the ability to test ngl
            elsif rising_edge(pi_clk) then 
                if pi_we = '1' then  
                    RAM(to_integer(unsigned(pi_addr))) <= pi_data;
                    po_data <= pi_data; 
                    -- if we set the po_data to the ram of pi_addr on a write enable case we get old data since it cant update faste enough
                    -- idk how to fix this better than this
                end if;
            end if;
        end process;
end architecture;

Tiefenmoser_Cornelius_Versuch1_Aufgabe1/Testbenches/RAM/Single_Port_RAM_tb.vhdl
library ieee;
use ieee.std_logic_1164.all;
use ieee.math_real.all;
use ieee.numeric_std.all;
use work.constant_package.all;




entity Single_Port_RAM_tb is
end entity;


architecture behavior of Single_Port_RAM_tb is
    signal s_clk, s_rst, s_we: std_logic := '0';
    
    
    signal s_addr : std_logic_vector (31 downto 0) := (others => '0');
    signal s_data : std_logic_vector(15 downto 0);
    signal s_dataout :std_logic_vector (15 downto 0);
    signal s_expected : std_logic_vector( 15 downto 0);
    
    -- Why do i get different results for different clock times??????
    constant c_clk_period : time := 10 ns;

    begin
    -- CLK Process aus der übung von Stefanie Häberle 
    clk_process : process
        begin
            while now < 200 ns loop  -- Simulation fuer 200 ns
                s_clk <= '0';
                wait for c_clk_period / 2;
                s_clk <= '1';
                wait for c_clk_period / 2;
            end loop;
            wait;
    end process;

    ram:entity work.single_port_ram
        generic map(16,32)
        port map(
            pi_data => s_data,
            pi_addr => s_addr,
            
            pi_we => s_we,
            pi_clk => s_clk,
            pi_rst => s_rst,

            po_data => s_dataout
        );


    spr_test: process is             
        begin
            s_addr <= (others => '0');
            -- cant test for 32 adr range as ghdl gives me weird range bug errors
            for i in 0 to 15 loop
                
                s_data <= (others => '1');
                s_we <= '1'; 
                s_expected <= (others => '0');
                s_rst <= '1';
                wait for c_clk_period;
                assert(s_dataout = s_expected) report ("Doesnt reset to 0") severity error;
                
                
                s_rst <= '0'; 
                s_data <= (others => '1');
                s_we <= '1'; 
                s_expected <= (others => '1');
                wait for c_clk_period;
                assert(s_dataout = s_expected) report ("Data doesnt set to 1 with we = 1 actual value of s_dataout: " & to_string(s_dataout))
                severity error;

                s_data <= (others => '0');
                s_we <= '1'; 
                s_expected <= (others => '0');
                wait for c_clk_period;
                assert(s_dataout = s_expected) report ("Data doesnt set to 0 with we = 1 actual value of s_dataout: " & to_string(s_dataout)) 
                severity error;

                s_data <= (others => '1');
                s_we <= '0'; 
                s_expected <= (others => '0');
                wait for c_clk_period;
                assert(s_dataout = s_expected) report ("Data sets to 1 despite we = 0") severity error;

                assert false report "End of test for address: " & to_string(s_addr) severity note;
                s_addr <= std_logic_vector(to_unsigned(2**i,s_addr'length) ); 
            end loop;
        end process;                


end architecture;

Tiefenmoser_Cornelius_Versuch1_Aufgabe1/ram_tb.vcd
$date
  Mon May  5 14:04:34 2025
$end
$version
  GHDL v0
$end
$timescale
  1 fs
$end
$scope module standard $end
$upscope $end
$scope module textio $end
$upscope $end
$scope module std_logic_1164 $end
$upscope $end
$scope module math_real $end
$upscope $end
$scope module numeric_std $end
$upscope $end
$scope module constant_package $end
$upscope $end
$scope module single_port_ram_tb $end
$var reg 1 ! s_clk $end
$var reg 1 " s_rst $end
$var reg 1 # s_we $end
$var reg 32 $ s_addr[31:0] $end
$var reg 16 % s_data[15:0] $end
$var reg 16 & s_dataout[15:0] $end
$var reg 16 ' s_expected[15:0] $end
$scope module ram $end
$var reg 16 ( pi_data[15:0] $end
$var reg 32 ) pi_addr[31:0] $end
$var reg 1 * pi_we $end
$var reg 1 + pi_rst $end
$var reg 1 , pi_clk $end
$var reg 16 - po_data[15:0] $end
$comment ram is not handled $end
$upscope $end
$upscope $end
$enddefinitions $end
#0
0!
1"
1#
b00000000000000000000000000000000 $
b1111111111111111 %
b0000000000000000 &
b0000000000000000 '
b1111111111111111 (
b00000000000000000000000000000000 )
1*
1+
0,
b0000000000000000 -
#5000000
1!
1,
#10000000
0!
0"
b1111111111111111 '
0+
0,
#15000000
1!
b1111111111111111 &
1,
b1111111111111111 -
#20000000
0!
b0000000000000000 %
b0000000000000000 '
b0000000000000000 (
0,
#25000000
1!
b0000000000000000 &
1,
b0000000000000000 -
#30000000
0!
0#
b1111111111111111 %
b1111111111111111 (
0*
0,
#35000000
1!
1,
#40000000
0!
1"
1#
b00000000000000000000000000000001 $
b00000000000000000000000000000001 )
1*
1+
0,
#45000000
1!
1,
#50000000
0!
0"
b1111111111111111 '
0+
0,
#55000000
1!
b1111111111111111 &
1,
b1111111111111111 -
#60000000
0!
b0000000000000000 %
b0000000000000000 '
b0000000000000000 (
0,
#65000000
1!
b0000000000000000 &
1,
b0000000000000000 -
#70000000
0!
0#
b1111111111111111 %
b1111111111111111 (
0*
0,
#75000000
1!
1,
#80000000
0!
1"
1#
b00000000000000000000000000000010 $
b00000000000000000000000000000010 )
1*
1+
0,
#85000000
1!
1,
#90000000
0!
0"
b1111111111111111 '
0+
0,
#95000000
1!
b1111111111111111 &
1,
b1111111111111111 -
#100000000
0!
b0000000000000000 %
b0000000000000000 '
b0000000000000000 (
0,
#105000000
1!
b0000000000000000 &
1,
b0000000000000000 -
#110000000
0!
0#
b1111111111111111 %
b1111111111111111 (
0*
0,
#115000000
1!
1,
#120000000
0!
1"
1#
b00000000000000000000000000000100 $
b00000000000000000000000000000100 )
1*
1+
0,
#125000000
1!
1,
#130000000
0!
0"
b1111111111111111 '
0+
0,
#135000000
1!
b1111111111111111 &
1,
b1111111111111111 -
#140000000
0!
b0000000000000000 %
b0000000000000000 '
b0000000000000000 (
0,
#145000000
1!
b0000000000000000 &
1,
b0000000000000000 -
#150000000
0!
0#
b1111111111111111 %
b1111111111111111 (
0*
0,
#155000000
1!
1,
#160000000
0!
1"
1#
b00000000000000000000000000001000 $
b00000000000000000000000000001000 )
1*
1+
0,
#165000000
1!
1,
#170000000
0!
0"
b1111111111111111 '
0+
0,
#175000000
1!
b1111111111111111 &
1,
b1111111111111111 -
#180000000
0!
b0000000000000000 %
b0000000000000000 '
b0000000000000000 (
0,
#185000000
1!
b0000000000000000 &
1,
b0000000000000000 -
#190000000
0!
0#
b1111111111111111 %
b1111111111111111 (
0*
0,
#195000000
1!
1,
#200000000
1"
1#
b00000000000000000000000000010000 $
b00000000000000000000000000010000 )
1*
1+
#210000000
0"
b1111111111111111 '
0+
#220000000
b0000000000000000 %
b0000000000000000 '
b0000000000000000 (
#230000000
0#
b1111111111111111 %
b1111111111111111 (
0*
#240000000
1"
1#
b00000000000000000000000000100000 $
b00000000000000000000000000100000 )
1*
1+
#250000000
0"
b1111111111111111 '
0+
#260000000
b0000000000000000 %
b0000000000000000 '
b0000000000000000 (
#270000000
0#
b1111111111111111 %
b1111111111111111 (
0*
#280000000
1"
1#
b00000000000000000000000001000000 $
b00000000000000000000000001000000 )
1*
1+
#290000000
0"
b1111111111111111 '
0+
#300000000
b0000000000000000 %
b0000000000000000 '
b0000000000000000 (
#310000000
0#
b1111111111111111 %
b1111111111111111 (
0*
#320000000
1"
1#
b00000000000000000000000010000000 $
b00000000000000000000000010000000 )
1*
1+
#330000000
0"
b1111111111111111 '
0+
#340000000
b0000000000000000 %
b0000000000000000 '
b0000000000000000 (
#350000000
0#
b1111111111111111 %
b1111111111111111 (
0*
#360000000
1"
1#
b00000000000000000000000100000000 $
b00000000000000000000000100000000 )
1*
1+
#370000000
0"
b1111111111111111 '
0+
#380000000
b0000000000000000 %
b0000000000000000 '
b0000000000000000 (
#390000000
0#
b1111111111111111 %
b1111111111111111 (
0*
#400000000
1"
1#
b00000000000000000000001000000000 $
b00000000000000000000001000000000 )
1*
1+
#410000000
0"
b1111111111111111 '
0+
#420000000
b0000000000000000 %
b0000000000000000 '
b0000000000000000 (
#430000000
0#
b1111111111111111 %
b1111111111111111 (
0*
#440000000
1"
1#
b00000000000000000000010000000000 $
b00000000000000000000010000000000 )
1*
1+
#450000000
0"
b1111111111111111 '
0+
#460000000
b0000000000000000 %
b0000000000000000 '
b0000000000000000 (
#470000000
0#
b1111111111111111 %
b1111111111111111 (
0*
#480000000
1"
1#
b00000000000000000000100000000000 $
b00000000000000000000100000000000 )
1*
1+
#490000000
0"
b1111111111111111 '
0+
#500000000
b0000000000000000 %
b0000000000000000 '
b0000000000000000 (
#510000000
0#
b1111111111111111 %
b1111111111111111 (
0*
#520000000
1"
1#
b00000000000000000001000000000000 $
b00000000000000000001000000000000 )
1*
1+
#530000000
0"
b1111111111111111 '
0+
#540000000
b0000000000000000 %
b0000000000000000 '
b0000000000000000 (
#550000000
0#
b1111111111111111 %
b1111111111111111 (
0*
#560000000
1"
1#
b00000000000000000010000000000000 $
b00000000000000000010000000000000 )
1*
1+
#570000000
0"
b1111111111111111 '
0+
#580000000
b0000000000000000 %
b0000000000000000 '
b0000000000000000 (
#590000000
0#
b1111111111111111 %
b1111111111111111 (
0*
#600000000
1"
1#
b00000000000000000100000000000000 $
b00000000000000000100000000000000 )
1*
1+
#610000000
0"
b1111111111111111 '
0+
#620000000
b0000000000000000 %
b0000000000000000 '
b0000000000000000 (
#630000000
0#
b1111111111111111 %
b1111111111111111 (
0*
#640000000
1"
1#
b00000000000000000000000000000000 $
b00000000000000000000000000000000 )
1*
1+
#650000000
0"
b1111111111111111 '
0+
#660000000
b0000000000000000 %
b0000000000000000 '
b0000000000000000 (
#670000000
0#
b1111111111111111 %
b1111111111111111 (
0*
#680000000
1"
1#
b00000000000000000000000000000001 $
b00000000000000000000000000000001 )
1*
1+
#690000000
0"
b1111111111111111 '
0+
#700000000
b0000000000000000 %
b0000000000000000 '
b0000000000000000 (
#710000000
0#
b1111111111111111 %
b1111111111111111 (
0*
#720000000
1"
1#
b00000000000000000000000000000010 $
b00000000000000000000000000000010 )
1*
1+
#730000000
0"
b1111111111111111 '
0+
#740000000
b0000000000000000 %
b0000000000000000 '
b0000000000000000 (
#750000000
0#
b1111111111111111 %
b1111111111111111 (
0*
#760000000
1"
1#
b00000000000000000000000000000100 $
b00000000000000000000000000000100 )
1*
1+
#770000000
0"
b1111111111111111 '
0+
#780000000
b0000000000000000 %
b0000000000000000 '
b0000000000000000 (
#790000000
0#
b1111111111111111 %
b1111111111111111 (
0*
#800000000
1"
1#
b00000000000000000000000000001000 $
b00000000000000000000000000001000 )
1*
1+
#810000000
0"
b1111111111111111 '
0+
#820000000
b0000000000000000 %
b0000000000000000 '
b0000000000000000 (
#830000000
0#
b1111111111111111 %
b1111111111111111 (
0*
#840000000
1"
1#
b00000000000000000000000000010000 $
b00000000000000000000000000010000 )
1*
1+
#850000000
0"
b1111111111111111 '
0+
#860000000
b0000000000000000 %
b0000000000000000 '
b0000000000000000 (
#870000000
0#
b1111111111111111 %
b1111111111111111 (
0*
#880000000
1"
1#
b00000000000000000000000000100000 $
b00000000000000000000000000100000 )
1*
1+
#890000000
0"
b1111111111111111 '
0+
#900000000
b0000000000000000 %
b0000000000000000 '
b0000000000000000 (
#910000000
0#
b1111111111111111 %
b1111111111111111 (
0*
#920000000
1"
1#
b00000000000000000000000001000000 $
b00000000000000000000000001000000 )
1*
1+
#930000000
0"
b1111111111111111 '
0+
#940000000
b0000000000000000 %
b0000000000000000 '
b0000000000000000 (
#950000000
0#
b1111111111111111 %
b1111111111111111 (
0*
#960000000
1"
1#
b00000000000000000000000010000000 $
b00000000000000000000000010000000 )
1*
1+
#970000000
0"
b1111111111111111 '
0+
#980000000
b0000000000000000 %
b0000000000000000 '
b0000000000000000 (
#990000000
0#
b1111111111111111 %
b1111111111111111 (
0*
#1000000000
1"
1#
b00000000000000000000000100000000 $
b00000000000000000000000100000000 )
1*
1+
#1010000000
0"
b1111111111111111 '
0+
#1020000000
b0000000000000000 %
b0000000000000000 '
b0000000000000000 (
#1030000000
0#
b1111111111111111 %
b1111111111111111 (
0*
#1040000000
1"
1#
b00000000000000000000001000000000 $
b00000000000000000000001000000000 )
1*
1+
#1050000000
0"
b1111111111111111 '
0+
#1060000000
b0000000000000000 %
b0000000000000000 '
b0000000000000000 (
#1070000000
0#
b1111111111111111 %
b1111111111111111 (
0*
#1080000000
1"
1#
b00000000000000000000010000000000 $
b00000000000000000000010000000000 )
1*
1+
#1090000000
0"
b1111111111111111 '
0+
#1100000000
b0000000000000000 %
b0000000000000000 '
b0000000000000000 (
#1110000000
0#
b1111111111111111 %
b1111111111111111 (
0*
#1120000000
1"
1#
b00000000000000000000100000000000 $
b00000000000000000000100000000000 )
1*
1+
#1130000000
0"
b1111111111111111 '
0+
#1140000000
b0000000000000000 %
b0000000000000000 '
b0000000000000000 (
#1150000000
0#
b1111111111111111 %
b1111111111111111 (
0*
#1160000000
1"
1#
b00000000000000000001000000000000 $
b00000000000000000001000000000000 )
1*
1+
#1170000000
0"
b1111111111111111 '
0+
#1180000000
b0000000000000000 %
b0000000000000000 '
b0000000000000000 (
#1190000000
0#
b1111111111111111 %
b1111111111111111 (
0*
#1200000000
1"
1#
b00000000000000000010000000000000 $
b00000000000000000010000000000000 )
1*
1+
#1210000000
0"
b1111111111111111 '
0+
#1220000000
b0000000000000000 %
b0000000000000000 '
b0000000000000000 (
#1230000000
0#
b1111111111111111 %
b1111111111111111 (
0*
#1240000000
1"
1#
b00000000000000000100000000000000 $
b00000000000000000100000000000000 )
1*
1+
#1250000000
0"
b1111111111111111 '
0+
#1260000000
b0000000000000000 %
b0000000000000000 '
b0000000000000000 (
#1270000000
0#
b1111111111111111 %
b1111111111111111 (
0*
#1280000000
1"
1#
b00000000000000000000000000000000 $
b00000000000000000000000000000000 )
1*
1+
#1290000000
0"
b1111111111111111 '
0+
#1300000000
b0000000000000000 %
b0000000000000000 '
b0000000000000000 (
#1310000000
0#
b1111111111111111 %
b1111111111111111 (
0*
#1320000000
1"
1#
b00000000000000000000000000000001 $
b00000000000000000000000000000001 )
1*
1+
#1330000000
0"
b1111111111111111 '
0+
#1340000000
b0000000000000000 %
b0000000000000000 '
b0000000000000000 (
#1350000000
0#
b1111111111111111 %
b1111111111111111 (
0*
#1360000000
1"
1#
b00000000000000000000000000000010 $
b00000000000000000000000000000010 )
1*
1+
#1370000000
0"
b1111111111111111 '
0+
#1380000000
b0000000000000000 %
b0000000000000000 '
b0000000000000000 (
#1390000000
0#
b1111111111111111 %
b1111111111111111 (
0*
#1400000000
1"
1#
b00000000000000000000000000000100 $
b00000000000000000000000000000100 )
1*
1+
#1410000000
0"
b1111111111111111 '
0+
#1420000000
b0000000000000000 %
b0000000000000000 '
b0000000000000000 (
#1430000000
0#
b1111111111111111 %
b1111111111111111 (
0*
#1440000000
1"
1#
b00000000000000000000000000001000 $
b00000000000000000000000000001000 )
1*
1+
#1450000000
0"
b1111111111111111 '
0+
#1460000000
b0000000000000000 %
b0000000000000000 '
b0000000000000000 (
#1470000000
0#
b1111111111111111 %
b1111111111111111 (
0*
#1480000000
1"
1#
b00000000000000000000000000010000 $
b00000000000000000000000000010000 )
1*
1+
#1490000000
0"
b1111111111111111 '
0+
#1500000000
b0000000000000000 %
b0000000000000000 '
b0000000000000000 (
#1510000000
0#
b1111111111111111 %
b1111111111111111 (
0*
#1520000000
1"
1#
b00000000000000000000000000100000 $
b00000000000000000000000000100000 )
1*
1+
#1530000000
0"
b1111111111111111 '
0+
#1540000000
b0000000000000000 %
b0000000000000000 '
b0000000000000000 (
#1550000000
0#
b1111111111111111 %
b1111111111111111 (
0*
#1560000000
1"
1#
b00000000000000000000000001000000 $
b00000000000000000000000001000000 )
1*
1+
#1570000000
0"
b1111111111111111 '
0+
#1580000000
b0000000000000000 %
b0000000000000000 '
b0000000000000000 (
#1590000000
0#
b1111111111111111 %
b1111111111111111 (
0*
#1600000000
1"
1#
b00000000000000000000000010000000 $
b00000000000000000000000010000000 )
1*
1+
#1610000000
0"
b1111111111111111 '
0+
#1620000000
b0000000000000000 %
b0000000000000000 '
b0000000000000000 (
#1630000000
0#
b1111111111111111 %
b1111111111111111 (
0*
#1640000000
1"
1#
b00000000000000000000000100000000 $
b00000000000000000000000100000000 )
1*
1+
#1650000000
0"
b1111111111111111 '
0+
#1660000000
b0000000000000000 %
b0000000000000000 '
b0000000000000000 (
#1670000000
0#
b1111111111111111 %
b1111111111111111 (
0*
#1680000000
1"
1#
b00000000000000000000001000000000 $
b00000000000000000000001000000000 )
1*
1+
#1690000000
0"
b1111111111111111 '
0+
#1700000000
b0000000000000000 %
b0000000000000000 '
b0000000000000000 (
#1710000000
0#
b1111111111111111 %
b1111111111111111 (
0*
#1720000000
1"
1#
b00000000000000000000010000000000 $
b00000000000000000000010000000000 )
1*
1+
#1730000000
0"
b1111111111111111 '
0+
#1740000000
b0000000000000000 %
b0000000000000000 '
b0000000000000000 (
#1750000000
0#
b1111111111111111 %
b1111111111111111 (
0*
#1760000000
1"
1#
b00000000000000000000100000000000 $
b00000000000000000000100000000000 )
1*
1+
#1770000000
0"
b1111111111111111 '
0+
#1780000000
b0000000000000000 %
b0000000000000000 '
b0000000000000000 (
#1790000000
0#
b1111111111111111 %
b1111111111111111 (
0*
#1800000000
1"
1#
b00000000000000000001000000000000 $
b00000000000000000001000000000000 )
1*
1+
#1810000000
0"
b1111111111111111 '
0+
#1820000000
b0000000000000000 %
b0000000000000000 '
b0000000000000000 (
#1830000000
0#
b1111111111111111 %
b1111111111111111 (
0*
#1840000000
1"
1#
b00000000000000000010000000000000 $
b00000000000000000010000000000000 )
1*
1+
#1850000000
0"
b1111111111111111 '
0+
#1860000000
b0000000000000000 %
b0000000000000000 '
b0000000000000000 (
#1870000000
0#
b1111111111111111 %
b1111111111111111 (
0*
#1880000000
1"
1#
b00000000000000000100000000000000 $
b00000000000000000100000000000000 )
1*
1+
#1890000000
0"
b1111111111111111 '
0+
#1900000000
b0000000000000000 %
b0000000000000000 '
b0000000000000000 (
#1910000000
0#
b1111111111111111 %
b1111111111111111 (
0*
#1920000000
1"
1#
b00000000000000000000000000000000 $
b00000000000000000000000000000000 )
1*
1+
#1930000000
0"
b1111111111111111 '
0+
#1940000000
b0000000000000000 %
b0000000000000000 '
b0000000000000000 (
#1950000000
0#
b1111111111111111 %
b1111111111111111 (
0*
#1960000000
1"
1#
b00000000000000000000000000000001 $
b00000000000000000000000000000001 )
1*
1+
#1970000000
0"
b1111111111111111 '
0+
#1980000000
b0000000000000000 %
b0000000000000000 '
b0000000000000000 (
#1990000000
0#
b1111111111111111 %
b1111111111111111 (
0*
#2000000000
1"
1#
b00000000000000000000000000000010 $
b00000000000000000000000000000010 )
1*
1+
#2010000000
0"
b1111111111111111 '
0+
#2020000000
b0000000000000000 %
b0000000000000000 '
b0000000000000000 (
#2030000000
0#
b1111111111111111 %
b1111111111111111 (
0*
#2040000000
1"
1#
b00000000000000000000000000000100 $
b00000000000000000000000000000100 )
1*
1+
#2050000000
0"
b1111111111111111 '
0+
#2060000000
b0000000000000000 %
b0000000000000000 '
b0000000000000000 (
#2070000000
0#
b1111111111111111 %
b1111111111111111 (
0*
#2080000000
1"
1#
b00000000000000000000000000001000 $
b00000000000000000000000000001000 )
1*
1+
#2090000000
0"
b1111111111111111 '
0+
#2100000000
b0000000000000000 %
b0000000000000000 '
b0000000000000000 (
#2110000000
0#
b1111111111111111 %
b1111111111111111 (
0*
#2120000000
1"
1#
b00000000000000000000000000010000 $
b00000000000000000000000000010000 )
1*
1+
#2130000000
0"
b1111111111111111 '
0+
#2140000000
b0000000000000000 %
b0000000000000000 '
b0000000000000000 (
#2150000000
0#
b1111111111111111 %
b1111111111111111 (
0*
#2160000000
1"
1#
b00000000000000000000000000100000 $
b00000000000000000000000000100000 )
1*
1+
#2170000000
0"
b1111111111111111 '
0+
#2180000000
b0000000000000000 %
b0000000000000000 '
b0000000000000000 (
#2190000000
0#
b1111111111111111 %
b1111111111111111 (
0*
#2200000000
1"
1#
b00000000000000000000000001000000 $
b00000000000000000000000001000000 )
1*
1+
#2210000000
0"
b1111111111111111 '
0+
#2220000000
b0000000000000000 %
b0000000000000000 '
b0000000000000000 (
#2230000000
0#
b1111111111111111 %
b1111111111111111 (
0*
#2240000000
1"
1#
b00000000000000000000000010000000 $
b00000000000000000000000010000000 )
1*
1+
#2250000000
0"
b1111111111111111 '
0+
#2260000000
b0000000000000000 %
b0000000000000000 '
b0000000000000000 (
#2270000000
0#
b1111111111111111 %
b1111111111111111 (
0*
#2280000000
1"
1#
b00000000000000000000000100000000 $
b00000000000000000000000100000000 )
1*
1+
#2290000000
0"
b1111111111111111 '
0+
#2300000000
b0000000000000000 %
b0000000000000000 '
b0000000000000000 (
#2310000000
0#
b1111111111111111 %
b1111111111111111 (
0*
#2320000000
1"
1#
b00000000000000000000001000000000 $
b00000000000000000000001000000000 )
1*
1+
#2330000000
0"
b1111111111111111 '
0+
#2340000000
b0000000000000000 %
b0000000000000000 '
b0000000000000000 (
#2350000000
0#
b1111111111111111 %
b1111111111111111 (
0*
#2360000000
1"
1#
b00000000000000000000010000000000 $
b00000000000000000000010000000000 )
1*
1+
#2370000000
0"
b1111111111111111 '
0+
#2380000000
b0000000000000000 %
b0000000000000000 '
b0000000000000000 (
#2390000000
0#
b1111111111111111 %
b1111111111111111 (
0*
#2400000000
1"
1#
b00000000000000000000100000000000 $
b00000000000000000000100000000000 )
1*
1+
#2410000000
0"
b1111111111111111 '
0+
#2420000000
b0000000000000000 %
b0000000000000000 '
b0000000000000000 (
#2430000000
0#
b1111111111111111 %
b1111111111111111 (
0*
#2440000000
1"
1#
b00000000000000000001000000000000 $
b00000000000000000001000000000000 )
1*
1+
#2450000000
0"
b1111111111111111 '
0+
#2460000000
b0000000000000000 %
b0000000000000000 '
b0000000000000000 (
#2470000000
0#
b1111111111111111 %
b1111111111111111 (
0*
#2480000000
1"
1#
b00000000000000000010000000000000 $
b00000000000000000010000000000000 )
1*
1+
#2490000000
0"
b1111111111111111 '
0+
#2500000000
b0000000000000000 %
b0000000000000000 '
b0000000000000000 (
#2510000000
0#
b1111111111111111 %
b1111111111111111 (
0*
#2520000000
1"
1#
b00000000000000000100000000000000 $
b00000000000000000100000000000000 )
1*
1+
#2530000000
0"
b1111111111111111 '
0+
#2540000000
b0000000000000000 %
b0000000000000000 '
b0000000000000000 (
#2550000000
0#
b1111111111111111 %
b1111111111111111 (
0*
#2560000000
1"
1#
b00000000000000000000000000000000 $
b00000000000000000000000000000000 )
1*
1+
#2570000000
0"
b1111111111111111 '
0+
#2580000000
b0000000000000000 %
b0000000000000000 '
b0000000000000000 (
#2590000000
0#
b1111111111111111 %
b1111111111111111 (
0*
#2600000000
1"
1#
b00000000000000000000000000000001 $
b00000000000000000000000000000001 )
1*
1+
#2610000000
0"
b1111111111111111 '
0+
#2620000000
b0000000000000000 %
b0000000000000000 '
b0000000000000000 (
#2630000000
0#
b1111111111111111 %
b1111111111111111 (
0*
#2640000000
1"
1#
b00000000000000000000000000000010 $
b00000000000000000000000000000010 )
1*
1+
#2650000000
0"
b1111111111111111 '
0+
#2660000000
b0000000000000000 %
b0000000000000000 '
b0000000000000000 (
#2670000000
0#
b1111111111111111 %
b1111111111111111 (
0*
#2680000000
1"
1#
b00000000000000000000000000000100 $
b00000000000000000000000000000100 )
1*
1+
#2690000000
0"
b1111111111111111 '
0+
#2700000000
b0000000000000000 %
b0000000000000000 '
b0000000000000000 (
#2710000000
0#
b1111111111111111 %
b1111111111111111 (
0*
#2720000000
1"
1#
b00000000000000000000000000001000 $
b00000000000000000000000000001000 )
1*
1+
#2730000000
0"
b1111111111111111 '
0+
#2740000000
b0000000000000000 %
b0000000000000000 '
b0000000000000000 (
#2750000000
0#
b1111111111111111 %
b1111111111111111 (
0*
#2760000000
1"
1#
b00000000000000000000000000010000 $
b00000000000000000000000000010000 )
1*
1+
#2770000000
0"
b1111111111111111 '
0+
#2780000000
b0000000000000000 %
b0000000000000000 '
b0000000000000000 (
#2790000000
0#
b1111111111111111 %
b1111111111111111 (
0*
#2800000000
1"
1#
b00000000000000000000000000100000 $
b00000000000000000000000000100000 )
1*
1+
#2810000000
0"
b1111111111111111 '
0+
#2820000000
b0000000000000000 %
b0000000000000000 '
b0000000000000000 (
#2830000000
0#
b1111111111111111 %
b1111111111111111 (
0*
#2840000000
1"
1#
b00000000000000000000000001000000 $
b00000000000000000000000001000000 )
1*
1+
#2850000000
0"
b1111111111111111 '
0+
#2860000000
b0000000000000000 %
b0000000000000000 '
b0000000000000000 (
#2870000000
0#
b1111111111111111 %
b1111111111111111 (
0*
#2880000000
1"
1#
b00000000000000000000000010000000 $
b00000000000000000000000010000000 )
1*
1+
#2890000000
0"
b1111111111111111 '
0+
#2900000000
b0000000000000000 %
b0000000000000000 '
b0000000000000000 (
#2910000000
0#
b1111111111111111 %
b1111111111111111 (
0*
#2920000000
1"
1#
b00000000000000000000000100000000 $
b00000000000000000000000100000000 )
1*
1+
#2930000000
0"
b1111111111111111 '
0+
#2940000000
b0000000000000000 %
b0000000000000000 '
b0000000000000000 (
#2950000000
0#
b1111111111111111 %
b1111111111111111 (
0*
#2960000000
1"
1#
b00000000000000000000001000000000 $
b00000000000000000000001000000000 )
1*
1+
#2970000000
0"
b1111111111111111 '
0+
#2980000000
b0000000000000000 %
b0000000000000000 '
b0000000000000000 (
#2990000000
0#
b1111111111111111 %
b1111111111111111 (
0*
#3000000000
1"
1#
b00000000000000000000010000000000 $
b00000000000000000000010000000000 )
1*
1+
#3010000000
0"
b1111111111111111 '
0+
#3020000000
b0000000000000000 %
b0000000000000000 '
b0000000000000000 (
#3030000000
0#
b1111111111111111 %
b1111111111111111 (
0*
#3040000000
1"
1#
b00000000000000000000100000000000 $
b00000000000000000000100000000000 )
1*
1+
#3050000000
0"
b1111111111111111 '
0+
#3060000000
b0000000000000000 %
b0000000000000000 '
b0000000000000000 (
#3070000000
0#
b1111111111111111 %
b1111111111111111 (
0*
#3080000000
1"
1#
b00000000000000000001000000000000 $
b00000000000000000001000000000000 )
1*
1+
#3090000000
0"
b1111111111111111 '
0+
#3100000000
b0000000000000000 %
b0000000000000000 '
b0000000000000000 (
#3110000000
0#
b1111111111111111 %
b1111111111111111 (
0*
#3120000000
1"
1#
b00000000000000000010000000000000 $
b00000000000000000010000000000000 )
1*
1+
#3130000000
0"
b1111111111111111 '
0+
#3140000000
b0000000000000000 %
b0000000000000000 '
b0000000000000000 (
#3150000000
0#
b1111111111111111 %
b1111111111111111 (
0*
#3160000000
1"
1#
b00000000000000000100000000000000 $
b00000000000000000100000000000000 )
1*
1+
#3170000000
0"
b1111111111111111 '
0+
#3180000000
b0000000000000000 %
b0000000000000000 '
b0000000000000000 (
#3190000000
0#
b1111111111111111 %
b1111111111111111 (
0*
#3200000000
1"
1#
b00000000000000000000000000000000 $
b00000000000000000000000000000000 )
1*
1+
#3210000000
0"
b1111111111111111 '
0+
#3220000000
b0000000000000000 %
b0000000000000000 '
b0000000000000000 (
#3230000000
0#
b1111111111111111 %
b1111111111111111 (
0*
#3240000000
1"
1#
b00000000000000000000000000000001 $
b00000000000000000000000000000001 )
1*
1+
#3250000000
0"
b1111111111111111 '
0+
#3260000000
b0000000000000000 %
b0000000000000000 '
b0000000000000000 (
#3270000000
0#
b1111111111111111 %
b1111111111111111 (
0*
#3280000000
1"
1#
b00000000000000000000000000000010 $
b00000000000000000000000000000010 )
1*
1+
#3290000000
0"
b1111111111111111 '
0+
#3300000000
b0000000000000000 %
b0000000000000000 '
b0000000000000000 (
#3310000000
0#
b1111111111111111 %
b1111111111111111 (
0*
#3320000000
1"
1#
b00000000000000000000000000000100 $
b00000000000000000000000000000100 )
1*
1+
#3330000000
0"
b1111111111111111 '
0+
#3340000000
b0000000000000000 %
b0000000000000000 '
b0000000000000000 (
#3350000000
0#
b1111111111111111 %
b1111111111111111 (
0*
#3360000000
1"
1#
b00000000000000000000000000001000 $
b00000000000000000000000000001000 )
1*
1+
#3370000000
0"
b1111111111111111 '
0+
#3380000000
b0000000000000000 %
b0000000000000000 '
b0000000000000000 (
#3390000000
0#
b1111111111111111 %
b1111111111111111 (
0*
#3400000000
1"
1#
b00000000000000000000000000010000 $
b00000000000000000000000000010000 )
1*
1+
#3410000000
0"
b1111111111111111 '
0+
#3420000000
b0000000000000000 %
b0000000000000000 '
b0000000000000000 (
#3430000000
0#
b1111111111111111 %
b1111111111111111 (
0*
#3440000000
1"
1#
b00000000000000000000000000100000 $
b00000000000000000000000000100000 )
1*
1+
#3450000000
0"
b1111111111111111 '
0+
#3460000000
b0000000000000000 %
b0000000000000000 '
b0000000000000000 (
#3470000000
0#
b1111111111111111 %
b1111111111111111 (
0*
#3480000000
1"
1#
b00000000000000000000000001000000 $
b00000000000000000000000001000000 )
1*
1+
#3490000000
0"
b1111111111111111 '
0+
#3500000000
b0000000000000000 %
b0000000000000000 '
b0000000000000000 (
#3510000000
0#
b1111111111111111 %
b1111111111111111 (
0*
